CONTRIBUTING.rst
LICENSE
MANIFEST.in
Makefile
README.rst
requirements.txt
setup.py
tox.ini
pinball/__init__.py
pinball/run_pinball.py
pinball.egg-info/PKG-INFO
pinball.egg-info/SOURCES.txt
pinball.egg-info/dependency_links.txt
pinball.egg-info/not-zip-safe
pinball.egg-info/requires.txt
pinball.egg-info/top_level.txt
pinball/authentication/__init__.py
pinball/authentication/oauth2.py
pinball/common/__init__.py
pinball/common/s3_utils.py
pinball/config/__init__.py
pinball/config/pinball_config.py
pinball/config/utils.py
pinball/master/__init__.py
pinball/master/blessed_version.py
pinball/master/client.py
pinball/master/factory.py
pinball/master/master.py
pinball/master/master_handler.py
pinball/master/snapshot.py
pinball/master/transaction.py
pinball/master/thrift_lib/TokenMasterService.py
pinball/master/thrift_lib/__init__.py
pinball/master/thrift_lib/constants.py
pinball/master/thrift_lib/ttypes.py
pinball/parser/__init__.py
pinball/parser/config_parser.py
pinball/parser/repository_config_parser.py
pinball/parser/utils.py
pinball/persistence/__init__.py
pinball/persistence/models.py
pinball/persistence/store.py
pinball/persistence/token_data.py
pinball/scheduler/__init__.py
pinball/scheduler/overrun_policy.py
pinball/scheduler/schedule.py
pinball/scheduler/scheduler.py
pinball/tools/__init__.py
pinball/tools/base.py
pinball/tools/pinball_util.py
pinball/tools/workflow_util.py
pinball/ui/__init__.py
pinball/ui/cache_thread.py
pinball/ui/data.py
pinball/ui/data_builder.py
pinball/ui/urls.py
pinball/ui/utils.py
pinball/ui/views.py
pinball/ui/workflow_graph.py
pinball/ui/assets/css/jquery.dataTables.css
pinball/ui/assets/css/pinball.css
pinball/ui/assets/css/signin.css
pinball/ui/assets/css/bootstrap/bootstrap-responsive.css
pinball/ui/assets/css/bootstrap/bootstrap-responsive.min.css
pinball/ui/assets/css/bootstrap/bootstrap.css
pinball/ui/assets/css/bootstrap/bootstrap.min.css
pinball/ui/assets/css/bootstrap/images/glyphicons-halflings-white.png
pinball/ui/assets/css/bootstrap/images/glyphicons-halflings.png
pinball/ui/assets/css/bootstrap3/bootstrap-theme.css
pinball/ui/assets/css/bootstrap3/bootstrap-theme.min.css
