Metadata-Version: 1.1
Name: pinball
Version: 0.2.7
Summary: Workflow manager and scheduler
Home-page: https://github.com/pinterest/pinball
Author: Pawel Garbacki
Author-email: pawel@pinterest.com
License: Apache 2.0
Keywords: pinball,workflow manager,batch,job,hadoop,emr,qubole
Platform: UNKNOWN
Classifier: Development Status :: 5 - Production/Stable
Classifier: Intended Audience :: Developers
Classifier: Natural Language :: English
Classifier: Programming Language :: Python :: 2.7
Classifier: License :: OSI Approved :: Apache Software License
Classifier: Topic :: System :: Distributed Computing
